Workbook

Sheet Assumptions
B1: DCF MODEL — KEY ASSUMPTIONS
B3: Company Name | C3: Enter Company Name
B4: Valuation Date | C4: MM/DD/YYYY
B5: Currency | C5: USD ($mm)
B7: PROJECTION PERIOD
C8: Historical | D8: Historical | E8: Projected | F8: Projected | G8: Projected | H8: Projected | I8: Projected
B9: Year | C9: 2024 | D9: 2025 | E9: 2026 | F9: 2027 | G9: 2028 | H9: 2029 | I9: 2030
B11: REVENUE ASSUMPTIONS
B12: Revenue ($mm) | C12: 100 | D12: 120 | E12: =D12*(1+E13) -> 138 | F12: =E12*(1+F13) -> 158.7 | G12: =F12*(1+G13) -> 182.505 | H12: =G12*(1+H13) -> 209.88075 | I12: =H12*(1+I13) -> 241.36286
B13: Revenue Growth Rate | D13: 0.2 | E13: 0.15 | F13: 0.15 | G13: 0.15 | H13: 0.15 | I13: 0.15
B15: MARGIN ASSUMPTIONS
B16: COGS (% of Revenue) | C16: 0.4 | D16: 0.4 | E16: 0.4 | F16: 0.4 | G16: 0.4 | H16: 0.4 | I16: 0.4
B17: Gross Margin | C17: =1-C16 -> 0.6 | D17: =1-D16 -> 0.6 | E17: =1-E16 -> 0.6 | F17: =1-F16 -> 0.6 | G17: =1-G16 -> 0.6 | H17: =1-H16 -> 0.6 | I17: =1-I16 -> 0.6
B18: SG&A (% of Revenue) | C18: 0.2 | D18: 0.2 | E18: 0.2 | F18: 0.2 | G18: 0.2 | H18: 0.2 | I18: 0.2
B19: R&D (% of Revenue) | C19: 0.1 | D19: 0.1 | E19: 0.1 | F19: 0.1 | G19: 0.1 | H19: 0.1 | I19: 0.1
B20: D&A (% of Revenue) | C20: 0.05 | D20: 0.05 | E20: 0.05 | F20: 0.05 | G20: 0.05 | H20: 0.05 | I20: 0.05
B21: EBIT Margin | C21: =C17-C18-C19-C20 -> 0.25 | D21: =D17-D18-D19-D20 -> 0.25 | E21: =E17-E18-E19-E20 -> 0.25 | F21: =F17-F18-F19-F20 -> 0.25 | G21: =G17-G18-G19-G20 -> 0.25 | H21: =H17-H18-H19-H20 -> 0.25 | I21: =I17-I18-I19-I20 -> 0.25
B23: WACC ASSUMPTIONS
B24: Risk-Free Rate | C24: 0.04
B25: Equity Risk Premium | C25: 0.06
B26: Beta (Levered) | C26: 1.2
B27: Cost of Equity (CAPM) | C27: =C24+C26*C25 -> 0.112
B28: Pre-Tax Cost of Debt | C28: 0.05
B29: Tax Rate | C29: 0.25
B30: After-Tax Cost of Debt | C30: =C28*(1-C29) -> 0.0375
B31: Debt / Total Capital | C31: 0.3
B32: Equity / Total Capital | C32: =1-C31 -> 0.7
B33: WACC | C33: =C27*C32+C30*C31 -> 0.08965
B35: TERMINAL VALUE ASSUMPTIONS
B36: Terminal Growth Rate | C36: 0.025
B37: Exit Multiple (EV/EBITDA) | C37: 12
B39: BALANCE SHEET & EQUITY BRIDGE
B40: Cash & Equivalents ($mm) | C40: 50
B41: Total Debt ($mm) | C41: 200
B42: Shares Outstanding (mm) | C42: 100
B43: CapEx (% of Revenue) | C43: 0.08
B44: Change in NWC (% of Rev Change) | C44: 0.1

Sheet DCF Model
B1: UNLEVERED DCF MODEL
B3: Year | C3: =Assumptions!C9 -> 2024 | D3: =Assumptions!D9 -> 2025 | E3: =Assumptions!E9 -> 2026 | F3: =Assumptions!F9 -> 2027 | G3: =Assumptions!G9 -> 2028 | H3: =Assumptions!H9 -> 2029 | I3: =Assumptions!I9 -> 2030
B5: INCOME STATEMENT BUILDUP
B6: Revenue | C6: =Assumptions!C12 -> 100 | D6: =Assumptions!D12 -> 120 | E6: =Assumptions!E12 -> 138 | F6: =Assumptions!F12 -> 158.7 | G6: =Assumptions!G12 -> 182.505 | H6: =Assumptions!H12 -> 209.88075 | I6: =Assumptions!I12 -> 241.36286
B7: (-) COGS | C7: =-Assumptions!C16*C6 -> -40 | D7: =-Assumptions!D16*D6 -> -48 | E7: =-Assumptions!E16*E6 -> -55.2 | F7: =-Assumptions!F16*F6 -> -63.48 | G7: =-Assumptions!G16*G6 -> -73.002 | H7: =-Assumptions!H16*H6 -> -83.9523 | I7: =-Assumptions!I16*I6 -> -96.545145
B8: Gross Profit | C8: =C6+C7 -> 60 | D8: =D6+D7 -> 72 | E8: =E6+E7 -> 82.8 | F8: =F6+F7 -> 95.22 | G8: =G6+G7 -> 109.503 | H8: =H6+H7 -> 125.92845 | I8: =I6+I7 -> 144.81772
B9: (-) SG&A | C9: =-Assumptions!C18*C6 -> -20 | D9: =-Assumptions!D18*D6 -> -24 | E9: =-Assumptions!E18*E6 -> -27.6 | F9: =-Assumptions!F18*F6 -> -31.74 | G9: =-Assumptions!G18*G6 -> -36.501 | H9: =-Assumptions!H18*H6 -> -41.97615 | I9: =-Assumptions!I18*I6 -> -48.272573
B10: (-) R&D | C10: =-Assumptions!C19*C6 -> -10 | D10: =-Assumptions!D19*D6 -> -12 | E10: =-Assumptions!E19*E6 -> -13.8 | F10: =-Assumptions!F19*F6 -> -15.87 | G10: =-Assumptions!G19*G6 -> -18.2505 | H10: =-Assumptions!H19*H6 -> -20.988075 | I10: =-Assumptions!I19*I6 -> -24.136286
B11: (-) D&A | C11: =-Assumptions!C20*C6 -> -5 | D11: =-Assumptions!D20*D6 -> -6 | E11: =-Assumptions!E20*E6 -> -6.9 | F11: =-Assumptions!F20*F6 -> -7.935 | G11: =-Assumptions!G20*G6 -> -9.12525 | H11: =-Assumptions!H20*H6 -> -10.494037 | I11: =-Assumptions!I20*I6 -> -12.068143
B12: EBIT | C12: =C8+C9+C10+C11 -> 25 | D12: =D8+D9+D10+D11 -> 30 | E12: =E8+E9+E10+E11 -> 34.5 | F12: =F8+F9+F10+F11 -> 39.675 | G12: =G8+G9+G10+G11 -> 45.62625 | H12: =H8+H9+H10+H11 -> 52.470188 | I12: =I8+I9+I10+I11 -> 60.340716
B13: EBIT Margin | C13: =IF(C6=0,0,C12/C6) -> 0.25 | D13: =IF(D6=0,0,D12/D6) -> 0.25 | E13: =IF(E6=0,0,E12/E6) -> 0.25 | F13: =IF(F6=0,0,F12/F6) -> 0.25 | G13: =IF(G6=0,0,G12/G6) -> 0.25 | H13: =IF(H6=0,0,H12/H6) -> 0.25 | I13: =IF(I6=0,0,I12/I6) -> 0.25
B15: UNLEVERED FREE CASH FLOW
B16: EBIT | C16: =C12 -> 25 | D16: =D12 -> 30 | E16: =E12 -> 34.5 | F16: =F12 -> 39.675 | G16: =G12 -> 45.62625 | H16: =H12 -> 52.470188 | I16: =I12 -> 60.340716
B17: (-) Taxes on EBIT | C17: =-C16*Assumptions!$C$29 -> -6.25 | D17: =-D16*Assumptions!$C$29 -> -7.5 | E17: =-E16*Assumptions!$C$29 -> -8.625 | F17: =-F16*Assumptions!$C$29 -> -9.91875 | G17: =-G16*Assumptions!$C$29 -> -11.406562 | H17: =-H16*Assumptions!$C$29 -> -13.117547 | I17: =-I16*Assumptions!$C$29 -> -15.085179
B18: NOPAT | C18: =C16+C17 -> 18.75 | D18: =D16+D17 -> 22.5 | E18: =E16+E17 -> 25.875 | F18: =F16+F17 -> 29.75625 | G18: =G16+G17 -> 34.219687 | H18: =H16+H17 -> 39.352641 | I18: =I16+I17 -> 45.255537
B19: (+) D&A | C19: =-C11 -> 5 | D19: =-D11 -> 6 | E19: =-E11 -> 6.9 | F19: =-F11 -> 7.935 | G19: =-G11 -> 9.12525 | H19: =-H11 -> 10.494037 | I19: =-I11 -> 12.068143
B20: (-) CapEx | C20: =-Assumptions!$C$43*C6 -> -8 | D20: =-Assumptions!$C$43*D6 -> -9.6 | E20: =-Assumptions!$C$43*E6 -> -11.04 | F20: =-Assumptions!$C$43*F6 -> -12.696 | G20: =-Assumptions!$C$43*G6 -> -14.6004 | H20: =-Assumptions!$C$43*H6 -> -16.79046 | I20: =-Assumptions!$C$43*I6 -> -19.309029
B21: (-) Change in NWC | C21: 0 | D21: =-Assumptions!$C$44*(D6-C6) -> -2 | E21: =-Assumptions!$C$44*(E6-D6) -> -1.8 | F21: =-Assumptions!$C$44*(F6-E6) -> -2.07 | G21: =-Assumptions!$C$44*(G6-F6) -> -2.3805 | H21: =-Assumptions!$C$44*(H6-G6) -> -2.737575 | I21: =-Assumptions!$C$44*(I6-H6) -> -3.1482113
B22: Unlevered Free Cash Flow | C22: =C18+C19+C20+C21 -> 15.75 | D22: =D18+D19+D20+D21 -> 16.9 | E22: =E18+E19+E20+E21 -> 19.935 | F22: =F18+F19+F20+F21 -> 22.92525 | G22: =G18+G19+G20+G21 -> 26.364037 | H22: =H18+H19+H20+H21 -> 30.318643 | I22: =I18+I19+I20+I21 -> 34.86644
B24: TERMINAL VALUE & VALUATION
B25: WACC | C25: =Assumptions!C33 -> 0.08965
B26: Terminal Growth Rate | C26: =Assumptions!C36 -> 0.025
B28: Terminal Value (Gordon Growth) | C28: =I22*(1+C26)/(C25-C26) -> 552.79351
B29: Terminal Value (Exit Multiple) | C29: =(I12-I11)*Assumptions!C37 -> 868.9063
B31: PV of Projected FCFs | C31: =E22/(1+$C$25)^1+F22/(1+$C$25)^2+G22/(1+$C$25)^3+H22/(1+$C$25)^4+I22/(1+$C$25)^5 -> 102.1838
B32: PV of Terminal Value (Gordon Growth) | C32: =C28/(1+C25)^5 -> 359.85523
B33: PV of Terminal Value (Exit Multiple) | C33: =C29/(1+C25)^5 -> 565.63703
B35: EQUITY VALUE BRIDGE
B36: Enterprise Value (Gordon Growth) | C36: =C31+C32 -> 462.03903
B37: Enterprise Value (Exit Multiple) | C37: =C31+C33 -> 667.82083
B39: (+) Cash | C39: =Assumptions!C40 -> 50
B40: (-) Debt | C40: =-Assumptions!C41 -> -200
B42: Equity Value (Gordon Growth) | C42: =C36+C39+C40 -> 312.03903
B43: Equity Value (Exit Multiple) | C43: =C37+C39+C40 -> 517.82083
B45: Shares Outstanding (mm) | C45: =Assumptions!C42 -> 100
B47: Implied Share Price (Gordon Growth) | C47: =IF(C45=0,0,C42/C45) -> 3.1203903
B48: Implied Share Price (Exit Multiple) | C48: =IF(C45=0,0,C43/C45) -> 5.1782083

Sheet Sensitivity
B1: SENSITIVITY ANALYSIS — IMPLIED SHARE PRICE
B3: Gordon Growth Method
B4: WACC ↓ / g → | C4: 0.015 | D4: 0.02 | E4: 0.025 | F4: 0.03 | G4: 0.035
B5: 0.08 | C5: =('DCF Model'!C31*((1+'DCF Model'!C25)^5)/((1+$B$5)^5)+'DCF Model'!I22*(1+C$4)/($B$5-C$4)/(1+$B$5)^5+'DCF Model'!C39+'DCF Model'!C40)/'DCF Model'!C45 -> 3.2737674 | D5: =('DCF Model'!C31*((1+'DCF Model'!C25)^5)/((1+$B$5)^5)+'DCF Model'!I22*(1+D$4)/($B$5-D$4)/(1+$B$5)^5+'DCF Model'!C39+'DCF Model'!C40)/'DCF Model'!C45 -> 3.6023298 | E5: =('DCF Model'!C31*((1+'DCF Model'!C25)^5)/((1+$B$5)^5)+'DCF Model'!I22*(1+E$4)/($B$5-E$4)/(1+$B$5)^5+'DCF Model'!C39+'DCF Model'!C40)/'DCF Model'!C45 -> 3.990631 | F5: =('DCF Model'!C31*((1+'DCF Model'!C25)^5)/((1+$B$5)^5)+'DCF Model'!I22*(1+F$4)/($B$5-F$4)/(1+$B$5)^5+'DCF Model'!C39+'DCF Model'!C40)/'DCF Model'!C45 -> 4.4565923 | G5: =('DCF Model'!C31*((1+'DCF Model'!C25)^5)/((1+$B$5)^5)+'DCF Model'!I22*(1+G$4)/($B$5-G$4)/(1+$B$5)^5+'DCF Model'!C39+'DCF Model'!C40)/'DCF Model'!C45 -> 5.0261006
B6: 0.09 | C6: =('DCF Model'!C31*((1+'DCF Model'!C25)^5)/((1+$B$6)^5)+'DCF Model'!I22*(1+C$4)/($B$6-C$4)/(1+$B$6)^5+'DCF Model'!C39+'DCF Model'!C40)/'DCF Model'!C45 -> 2.5869592 | D6: =('DCF Model'!C31*((1+'DCF Model'!C25)^5)/((1+$B$6)^5)+'DCF Model'!I22*(1+D$4)/($B$6-D$4)/(1+$B$6)^5+'DCF Model'!C39+'DCF Model'!C40)/'DCF Model'!C45 -> 2.8221998 | E6: =('DCF Model'!C31*((1+'DCF Model'!C25)^5)/((1+$B$6)^5)+'DCF Model'!I22*(1+E$4)/($B$6-E$4)/(1+$B$6)^5+'DCF Model'!C39+'DCF Model'!C40)/'DCF Model'!C45 -> 3.0936313 | F6: =('DCF Model'!C31*((1+'DCF Model'!C25)^5)/((1+$B$6)^5)+'DCF Model'!I22*(1+F$4)/($B$6-F$4)/(1+$B$6)^5+'DCF Model'!C39+'DCF Model'!C40)/'DCF Model'!C45 -> 3.4103013 | G6: =('DCF Model'!C31*((1+'DCF Model'!C25)^5)/((1+$B$6)^5)+'DCF Model'!I22*(1+G$4)/($B$6-G$4)/(1+$B$6)^5+'DCF Model'!C39+'DCF Model'!C40)/'DCF Model'!C45 -> 3.7845478
B7: 0.1 | C7: =('DCF Model'!C31*((1+'DCF Model'!C25)^5)/((1+$B$7)^5)+'DCF Model'!I22*(1+C$4)/($B$7-C$4)/(1+$B$7)^5+'DCF Model'!C39+'DCF Model'!C40)/'DCF Model'!C45 -> 2.0598443 | D7: =('DCF Model'!C31*((1+'DCF Model'!C25)^5)/((1+$B$7)^5)+'DCF Model'!I22*(1+D$4)/($B$7-D$4)/(1+$B$7)^5+'DCF Model'!C39+'DCF Model'!C40)/'DCF Model'!C45 -> 2.2349491 | E7: =('DCF Model'!C31*((1+'DCF Model'!C25)^5)/((1+$B$7)^5)+'DCF Model'!I22*(1+E$4)/($B$7-E$4)/(1+$B$7)^5+'DCF Model'!C39+'DCF Model'!C40)/'DCF Model'!C45 -> 2.4334011 | F7: =('DCF Model'!C31*((1+'DCF Model'!C25)^5)/((1+$B$7)^5)+'DCF Model'!I22*(1+F$4)/($B$7-F$4)/(1+$B$7)^5+'DCF Model'!C39+'DCF Model'!C40)/'DCF Model'!C45 -> 2.6602035 | G7: =('DCF Model'!C31*((1+'DCF Model'!C25)^5)/((1+$B$7)^5)+'DCF Model'!I22*(1+G$4)/($B$7-G$4)/(1+$B$7)^5+'DCF Model'!C39+'DCF Model'!C40)/'DCF Model'!C45 -> 2.9218985
B8: 0.11 | C8: =('DCF Model'!C31*((1+'DCF Model'!C25)^5)/((1+$B$8)^5)+'DCF Model'!I22*(1+C$4)/($B$8-C$4)/(1+$B$8)^5+'DCF Model'!C39+'DCF Model'!C40)/'DCF Model'!C45 -> 1.6422687 | D8: =('DCF Model'!C31*((1+'DCF Model'!C25)^5)/((1+$B$8)^5)+'DCF Model'!I22*(1+D$4)/($B$8-D$4)/(1+$B$8)^5+'DCF Model'!C39+'DCF Model'!C40)/'DCF Model'!C45 -> 1.7765822 | E8: =('DCF Model'!C31*((1+'DCF Model'!C25)^5)/((1+$B$8)^5)+'DCF Model'!I22*(1+E$4)/($B$8-E$4)/(1+$B$8)^5+'DCF Model'!C39+'DCF Model'!C40)/'DCF Model'!C45 -> 1.9266973 | F8: =('DCF Model'!C31*((1+'DCF Model'!C25)^5)/((1+$B$8)^5)+'DCF Model'!I22*(1+F$4)/($B$8-F$4)/(1+$B$8)^5+'DCF Model'!C39+'DCF Model'!C40)/'DCF Model'!C45 -> 2.0955767 | G8: =('DCF Model'!C31*((1+'DCF Model'!C25)^5)/((1+$B$8)^5)+'DCF Model'!I22*(1+G$4)/($B$8-G$4)/(1+$B$8)^5+'DCF Model'!C39+'DCF Model'!C40)/'DCF Model'!C45 -> 2.2869734
B9: 0.12 | C9: =('DCF Model'!C31*((1+'DCF Model'!C25)^5)/((1+$B$9)^5)+'DCF Model'!I22*(1+C$4)/($B$9-C$4)/(1+$B$9)^5+'DCF Model'!C39+'DCF Model'!C40)/'DCF Model'!C45 -> 1.3031592 | D9: =('DCF Model'!C31*((1+'DCF Model'!C25)^5)/((1+$B$9)^5)+'DCF Model'!I22*(1+D$4)/($B$9-D$4)/(1+$B$9)^5+'DCF Model'!C39+'DCF Model'!C40)/'DCF Model'!C45 -> 1.4086747 | E9: =('DCF Model'!C31*((1+'DCF Model'!C25)^5)/((1+$B$9)^5)+'DCF Model'!I22*(1+E$4)/($B$9-E$4)/(1+$B$9)^5+'DCF Model'!C39+'DCF Model'!C40)/'DCF Model'!C45 -> 1.525297 | F9: =('DCF Model'!C31*((1+'DCF Model'!C25)^5)/((1+$B$9)^5)+'DCF Model'!I22*(1+F$4)/($B$9-F$4)/(1+$B$9)^5+'DCF Model'!C39+'DCF Model'!C40)/'DCF Model'!C45 -> 1.6548775 | G9: =('DCF Model'!C31*((1+'DCF Model'!C25)^5)/((1+$B$9)^5)+'DCF Model'!I22*(1+G$4)/($B$9-G$4)/(1+$B$9)^5+'DCF Model'!C39+'DCF Model'!C40)/'DCF Model'!C45 -> 1.7997027
B12: Note: Sensitivity table approximates share price across WACC and terminal growth rate scenarios.
