Workbook

Sheet Transaction
B1: LBO MODEL — TRANSACTION ASSUMPTIONS
B3: PURCHASE PRICE
B4: LTM EBITDA ($mm) | C4: 100
B5: Entry Multiple (EV/EBITDA) | C5: 10
B6: Enterprise Value ($mm) | C6: =C4*C5 -> 1000
B7: (-) Existing Debt ($mm) | C7: 50
B8: (+) Existing Cash ($mm) | C8: 20
B9: Equity Purchase Price ($mm) | C9: =C6-C7+C8 -> 970
B10: Transaction Fees ($mm) | C10: 15
B11: Total Uses ($mm) | C11: =C9+C10 -> 985
B13: SOURCES & USES
B14: SOURCES | C14: Amount ($mm) | D14: % of Total
B16: Senior Debt / EBITDA Multiple | C16: 4
B18: Senior Debt / Total Capital | C18: 0.5
B19: Sub Debt / Total Capital | C19: 0.2
B20: Sponsor Equity / Total Capital | C20: =1-C18-C19 -> 0.3
B22: SOURCES OF FUNDS
B23: Source | C23: Amount ($mm) | D23: % of Total
B24: Senior Secured Debt | C24: =C11*C18 -> 492.5 | D24: =IF(C27=0,0,C24/C27) -> 0.5
B25: Subordinated Debt | C25: =C11*C19 -> 197 | D25: =IF(C27=0,0,C25/C27) -> 0.2
B26: Sponsor Equity | C26: =C11-C24-C25 -> 295.5 | D26: =IF(C27=0,0,C26/C27) -> 0.3
B27: Total Sources | C27: =SUM(C24:C26) -> 985 | D27: =SUM(D24:D26) -> 1
B29: DEBT TERMS
B30: Senior Debt Interest Rate | C30: 0.06
B31: Sub Debt Interest Rate | C31: 0.1
B32: Mandatory Amortization (% of Senior) | C32: 0.05
B33: Cash Sweep (% of Excess CF) | C33: 0.5
B35: OPERATING ASSUMPTIONS
B36: Revenue Year 0 ($mm) | C36: 500
B37: Revenue Growth Rate | C37: 0.08
B38: EBITDA Margin | C38: 0.2
B39: D&A (% of Revenue) | C39: 0.03
B40: CapEx (% of Revenue) | C40: 0.04
B41: Change in NWC (% of Rev Change) | C41: 0.1
B42: Tax Rate | C42: 0.25
B44: EXIT ASSUMPTIONS
B45: Holding Period (Years) | C45: 5
B46: Exit Multiple (EV/EBITDA) | C46: 10

Sheet Operating Model
B1: LBO OPERATING MODEL
C2: Entry | H2: Exit
B3: Year | C3: 0 | D3: 1 | E3: 2 | F3: 3 | G3: 4 | H3: 5
B5: INCOME STATEMENT
B6: Revenue | C6: =Transaction!C36 -> 500 | D6: =C6*(1+Transaction!$C$37) -> 540 | E6: =D6*(1+Transaction!$C$37) -> 583.2 | F6: =E6*(1+Transaction!$C$37) -> 629.856 | G6: =F6*(1+Transaction!$C$37) -> 680.24448 | H6: =G6*(1+Transaction!$C$37) -> 734.66404
B7: EBITDA | C7: =C6*Transaction!$C$38 -> 100 | D7: =D6*Transaction!$C$38 -> 108 | E7: =E6*Transaction!$C$38 -> 116.64 | F7: =F6*Transaction!$C$38 -> 125.9712 | G7: =G6*Transaction!$C$38 -> 136.0489 | H7: =H6*Transaction!$C$38 -> 146.93281
B8: (-) D&A | C8: =-C6*Transaction!$C$39 -> -15 | D8: =-D6*Transaction!$C$39 -> -16.2 | E8: =-E6*Transaction!$C$39 -> -17.496 | F8: =-F6*Transaction!$C$39 -> -18.89568 | G8: =-G6*Transaction!$C$39 -> -20.407334 | H8: =-H6*Transaction!$C$39 -> -22.039921
B9: EBIT | C9: =C7+C8 -> 85 | D9: =D7+D8 -> 91.8 | E9: =E7+E8 -> 99.144 | F9: =F7+F8 -> 107.07552 | G9: =G7+G8 -> 115.64156 | H9: =H7+H8 -> 124.89289
B10: (-) Senior Debt Interest | C10: =-'Debt Schedule'!C6*Transaction!$C$30 -> -29.55 | D10: =-'Debt Schedule'!D6*Transaction!$C$30 -> -27.713625 | E10: =-'Debt Schedule'!E6*Transaction!$C$30 -> -25.814932 | F10: =-'Debt Schedule'!F6*Transaction!$C$30 -> -23.730838 | G10: =-'Debt Schedule'!G6*Transaction!$C$30 -> -21.445757 | H10: =-'Debt Schedule'!H6*Transaction!$C$30 -> -18.94284
B11: (-) Sub Debt Interest | C11: =-'Debt Schedule'!C11*Transaction!$C$31 -> 0 | D11: =-'Debt Schedule'!D11*Transaction!$C$31 -> 0 | E11: =-'Debt Schedule'!E11*Transaction!$C$31 -> 0 | F11: =-'Debt Schedule'!F11*Transaction!$C$31 -> 0 | G11: =-'Debt Schedule'!G11*Transaction!$C$31 -> 0 | H11: =-'Debt Schedule'!H11*Transaction!$C$31 -> 0
B12: EBT | C12: =C9+C10+C11 -> 55.45 | D12: =D9+D10+D11 -> 64.086375 | E12: =E9+E10+E11 -> 73.329068 | F12: =F9+F10+F11 -> 83.344682 | G12: =G9+G10+G11 -> 94.195805 | H12: =H9+H10+H11 -> 105.95005
B13: (-) Taxes | C13: =-MAX(C12,0)*Transaction!$C$42 -> -13.8625 | D13: =-MAX(D12,0)*Transaction!$C$42 -> -16.021594 | E13: =-MAX(E12,0)*Transaction!$C$42 -> -18.332267 | F13: =-MAX(F12,0)*Transaction!$C$42 -> -20.836171 | G13: =-MAX(G12,0)*Transaction!$C$42 -> -23.548951 | H13: =-MAX(H12,0)*Transaction!$C$42 -> -26.487512
B14: Net Income | C14: =C12+C13 -> 41.5875 | D14: =D12+D13 -> 48.064781 | E14: =E12+E13 -> 54.996801 | F14: =F12+F13 -> 62.508512 | G14: =G12+G13 -> 70.646853 | H14: =H12+H13 -> 79.462535
B16: FREE CASH FLOW
B17: Net Income | C17: =C14 -> 41.5875 | D17: =D14 -> 48.064781 | E17: =E14 -> 54.996801 | F17: =F14 -> 62.508512 | G17: =G14 -> 70.646853 | H17: =H14 -> 79.462535
B18: (+) D&A | C18: =-C8 -> 15 | D18: =-D8 -> 16.2 | E18: =-E8 -> 17.496 | F18: =-F8 -> 18.89568 | G18: =-G8 -> 20.407334 | H18: =-H8 -> 22.039921
B19: (-) CapEx | C19: =-C6*Transaction!$C$40 -> -20 | D19: =-D6*Transaction!$C$40 -> -21.6 | E19: =-E6*Transaction!$C$40 -> -23.328 | F19: =-F6*Transaction!$C$40 -> -25.19424 | G19: =-G6*Transaction!$C$40 -> -27.209779 | H19: =-H6*Transaction!$C$40 -> -29.386562
B20: (-) Change in NWC | C20: 0 | D20: =-Transaction!$C$41*(D6-C6) -> -4 | E20: =-Transaction!$C$41*(E6-D6) -> -4.32 | F20: =-Transaction!$C$41*(F6-E6) -> -4.6656 | G20: =-Transaction!$C$41*(G6-F6) -> -5.038848 | H20: =-Transaction!$C$41*(H6-G6) -> -5.4419558
B21: Levered Free Cash Flow | C21: =C17+C18+C19+C20 -> 36.5875 | D21: =D17+D18+D19+D20 -> 38.664781 | E21: =E17+E18+E19+E20 -> 44.844801 | F21: =F17+F18+F19+F20 -> 51.544352 | G21: =G17+G18+G19+G20 -> 58.805561 | H21: =H17+H18+H19+H20 -> 66.673939

Sheet Debt Schedule
B1: DEBT SCHEDULE
B3: Year | C3: 0 | D3: 1 | E3: 2 | F3: 3 | G3: 4 | H3: 5
B5: SENIOR SECURED DEBT
B6: Beginning Balance | C6: =Transaction!C24 -> 492.5 | D6: =C9 -> 461.89375 | E6: =D9 -> 430.24886 | F6: =E9 -> 395.51396 | G6: =F9 -> 357.42928 | H6: =G9 -> 315.714
B7: (-) Mandatory Amortization | C7: =-MIN(C6,Transaction!$C$32*Transaction!$C$24) -> -24.625 | D7: =-MIN(D6,Transaction!$C$32*Transaction!$C$24) -> -24.625 | E7: =-MIN(E6,Transaction!$C$32*Transaction!$C$24) -> -24.625 | F7: =-MIN(F6,Transaction!$C$32*Transaction!$C$24) -> -24.625 | G7: =-MIN(G6,Transaction!$C$32*Transaction!$C$24) -> -24.625 | H7: =-MIN(H6,Transaction!$C$32*Transaction!$C$24) -> -24.625
B8: (-) Optional Prepayment (Cash Sweep) | C8: =-MIN(C6+C7,MAX(0,'Operating Model'!C21+C7)*Transaction!$C$33) -> -5.98125 | D8: =-MIN(D6+D7,MAX(0,'Operating Model'!D21+D7)*Transaction!$C$33) -> -7.0198906 | E8: =-MIN(E6+E7,MAX(0,'Operating Model'!E21+E7)*Transaction!$C$33) -> -10.109901 | F8: =-MIN(F6+F7,MAX(0,'Operating Model'!F21+F7)*Transaction!$C$33) -> -13.459676 | G8: =-MIN(G6+G7,MAX(0,'Operating Model'!G21+G7)*Transaction!$C$33) -> -17.09028 | H8: =-MIN(H6+H7,MAX(0,'Operating Model'!H21+H7)*Transaction!$C$33) -> -21.024469
B9: Ending Balance | C9: =C6+C7+C8 -> 461.89375 | D9: =D6+D7+D8 -> 430.24886 | E9: =E6+E7+E8 -> 395.51396 | F9: =F6+F7+F8 -> 357.42928 | G9: =G6+G7+G8 -> 315.714 | H9: =H6+H7+H8 -> 270.06453
B11: SUBORDINATED DEBT
B12: Beginning Balance | C12: =Transaction!C25 -> 197 | D12: =C13 -> 197 | E12: =D13 -> 197 | F12: =E13 -> 197 | G12: =F13 -> 197 | H12: =G13 -> 197
B13: Ending Balance (No Amortization) | C13: =C12 -> 197 | D13: =D12 -> 197 | E13: =E12 -> 197 | F13: =F12 -> 197 | G13: =G12 -> 197 | H13: =H12 -> 197
B15: Total Debt | C15: =C9+C13 -> 658.89375 | D15: =D9+D13 -> 627.24886 | E15: =E9+E13 -> 592.51396 | F15: =F9+F13 -> 554.42928 | G15: =G9+G13 -> 512.714 | H15: =H9+H13 -> 467.06453
B17: CREDIT METRICS
B18: Total Debt / EBITDA | C18: =IF('Operating Model'!C7=0,0,C15/'Operating Model'!C7) -> 6.5889375 | D18: =IF('Operating Model'!D7=0,0,D15/'Operating Model'!D7) -> 5.8078598 | E18: =IF('Operating Model'!E7=0,0,E15/'Operating Model'!E7) -> 5.0798522 | F18: =IF('Operating Model'!F7=0,0,F15/'Operating Model'!F7) -> 4.4012384 | G18: =IF('Operating Model'!G7=0,0,G15/'Operating Model'!G7) -> 3.768601 | H18: =IF('Operating Model'!H7=0,0,H15/'Operating Model'!H7) -> 3.1787627
B19: Interest Coverage (EBITDA / Interest) | C19: =IF(('Operating Model'!C10+'Operating Model'!C11)=0,0,'Operating Model'!C7/(-'Operating Model'!C10-'Operating Model'!C11)) -> 3.3840948 | D19: =IF(('Operating Model'!D10+'Operating Model'!D11)=0,0,'Operating Model'!D7/(-'Operating Model'!D10-'Operating Model'!D11)) -> 3.8970001 | E19: =IF(('Operating Model'!E10+'Operating Model'!E11)=0,0,'Operating Model'!E7/(-'Operating Model'!E10-'Operating Model'!E11)) -> 4.5183153 | F19: =IF(('Operating Model'!F10+'Operating Model'!F11)=0,0,'Operating Model'!F7/(-'Operating Model'!F10-'Operating Model'!F11)) -> 5.3083335 | G19: =IF(('Operating Model'!G10+'Operating Model'!G11)=0,0,'Operating Model'!G7/(-'Operating Model'!G10-'Operating Model'!G11)) -> 6.3438608 | H19: =IF(('Operating Model'!H10+'Operating Model'!H11)=0,0,'Operating Model'!H7/(-'Operating Model'!H10-'Operating Model'!H11)) -> 7.7566408

Sheet Returns
B1: LBO RETURNS ANALYSIS
B3: EXIT VALUATION
B4: Exit Year EBITDA ($mm) | C4: ='Operating Model'!H7 -> 146.93281
B5: Exit Multiple (EV/EBITDA) | C5: =Transaction!C46 -> 10
B6: Exit Enterprise Value ($mm) | C6: =C4*C5 -> 1469.3281
B7: (-) Net Debt at Exit ($mm) | C7: =-'Debt Schedule'!H15 -> -467.06453
B8: Exit Equity Value ($mm) | C8: =C6+C7 -> 1002.2635
B10: SPONSOR RETURNS
B11: Initial Sponsor Equity ($mm) | C11: =Transaction!C26 -> 295.5
B12: Exit Equity Value ($mm) | C12: =C8 -> 1002.2635
B14: MOIC (Multiple of Invested Capital) | C14: =IF(C11=0,0,C12/C11) -> 3.3917548
B15: IRR | C15: =IF(C11=0,0,(C12/C11)^(1/Transaction!C45)-1) -> 0.27668833
B17: VALUE CREATION BRIDGE
B18: Entry Equity | C18: =C11 -> 295.5
B19: (+) EBITDA Growth Effect | C19: =(C4-Transaction!C4)*Transaction!C5 -> 469.32808
B20: (+) Multiple Expansion Effect | C20: =C4*(C5-Transaction!C5) -> 0
B21: (+) Debt Paydown Effect | C21: =Transaction!C24+Transaction!C25+'Debt Schedule'!H15 -> 1156.5645
B22: Exit Equity (Check) | C22: =C18+C19+C20+C21 -> 1921.3926
B24: SENSITIVITY — IRR BY EXIT MULTIPLE & EBITDA GROWTH
B25: Exit Mult ↓ / Growth → | C25: 0.05 | D25: 0.08 | E25: 0.1 | F25: 0.12 | G25: 0.15
B26: 8 | C26: =IF(Transaction!C26=0,0,((Transaction!C4*(1+C$25)^Transaction!C45*$B$26-'Debt Schedule'!H15)/Transaction!C26)^(1/Transaction!C45)-1) -> 0.13392491 | D26: =IF(Transaction!C26=0,0,((Transaction!C4*(1+D$25)^Transaction!C45*$B$26-'Debt Schedule'!H15)/Transaction!C26)^(1/Transaction!C45)-1) -> 0.1910883 | E26: =IF(Transaction!C26=0,0,((Transaction!C4*(1+E$25)^Transaction!C45*$B$26-'Debt Schedule'!H15)/Transaction!C26)^(1/Transaction!C45)-1) -> 0.22685564 | F26: =IF(Transaction!C26=0,0,((Transaction!C4*(1+F$25)^Transaction!C45*$B$26-'Debt Schedule'!H15)/Transaction!C26)^(1/Transaction!C45)-1) -> 0.26116883 | G26: =IF(Transaction!C26=0,0,((Transaction!C4*(1+G$25)^Transaction!C45*$B$26-'Debt Schedule'!H15)/Transaction!C26)^(1/Transaction!C45)-1) -> 0.3104587
B27: 9 | C27: =IF(Transaction!C26=0,0,((Transaction!C4*(1+C$25)^Transaction!C45*$B$27-'Debt Schedule'!H15)/Transaction!C26)^(1/Transaction!C45)-1) -> 0.18193339 | D27: =IF(Transaction!C26=0,0,((Transaction!C4*(1+D$25)^Transaction!C45*$B$27-'Debt Schedule'!H15)/Transaction!C26)^(1/Transaction!C45)-1) -> 0.23684512 | E27: =IF(Transaction!C26=0,0,((Transaction!C4*(1+E$25)^Transaction!C45*$B$27-'Debt Schedule'!H15)/Transaction!C26)^(1/Transaction!C45)-1) -> 0.27158584 | F27: =IF(Transaction!C26=0,0,((Transaction!C4*(1+F$25)^Transaction!C45*$B$27-'Debt Schedule'!H15)/Transaction!C26)^(1/Transaction!C45)-1) -> 0.30514227 | G27: =IF(Transaction!C26=0,0,((Transaction!C4*(1+G$25)^Transaction!C45*$B$27-'Debt Schedule'!H15)/Transaction!C26)^(1/Transaction!C45)-1) -> 0.35367327
B28: 10 | C28: =IF(Transaction!C26=0,0,((Transaction!C4*(1+C$25)^Transaction!C45*$B$28-'Debt Schedule'!H15)/Transaction!C26)^(1/Transaction!C45)-1) -> 0.22321136 | D28: =IF(Transaction!C26=0,0,((Transaction!C4*(1+D$25)^Transaction!C45*$B$28-'Debt Schedule'!H15)/Transaction!C26)^(1/Transaction!C45)-1) -> 0.27668833 | E28: =IF(Transaction!C26=0,0,((Transaction!C4*(1+E$25)^Transaction!C45*$B$28-'Debt Schedule'!H15)/Transaction!C26)^(1/Transaction!C45)-1) -> 0.3107854 | F28: =IF(Transaction!C26=0,0,((Transaction!C4*(1+F$25)^Transaction!C45*$B$28-'Debt Schedule'!H15)/Transaction!C26)^(1/Transaction!C45)-1) -> 0.34388171 | G28: =IF(Transaction!C26=0,0,((Transaction!C4*(1+G$25)^Transaction!C45*$B$28-'Debt Schedule'!H15)/Transaction!C26)^(1/Transaction!C45)-1) -> 0.39198458
B29: 11 | C29: =IF(Transaction!C26=0,0,((Transaction!C4*(1+C$25)^Transaction!C45*$B$29-'Debt Schedule'!H15)/Transaction!C26)^(1/Transaction!C45)-1) -> 0.25956931 | D29: =IF(Transaction!C26=0,0,((Transaction!C4*(1+D$25)^Transaction!C45*$B$29-'Debt Schedule'!H15)/Transaction!C26)^(1/Transaction!C45)-1) -> 0.31210125 | E29: =IF(Transaction!C26=0,0,((Transaction!C4*(1+E$25)^Transaction!C45*$B$29-'Debt Schedule'!H15)/Transaction!C26)^(1/Transaction!C45)-1) -> 0.34578934 | F29: =IF(Transaction!C26=0,0,((Transaction!C4*(1+F$25)^Transaction!C45*$B$29-'Debt Schedule'!H15)/Transaction!C26)^(1/Transaction!C45)-1) -> 0.37860936 | G29: =IF(Transaction!C26=0,0,((Transaction!C4*(1+G$25)^Transaction!C45*$B$29-'Debt Schedule'!H15)/Transaction!C26)^(1/Transaction!C45)-1) -> 0.42649058
B30: 12 | C30: =IF(Transaction!C26=0,0,((Transaction!C4*(1+C$25)^Transaction!C45*$B$30-'Debt Schedule'!H15)/Transaction!C26)^(1/Transaction!C45)-1) -> 0.29215752 | D30: =IF(Transaction!C26=0,0,((Transaction!C4*(1+D$25)^Transaction!C45*$B$30-'Debt Schedule'!H15)/Transaction!C26)^(1/Transaction!C45)-1) -> 0.34405846 | E30: =IF(Transaction!C26=0,0,((Transaction!C4*(1+E$25)^Transaction!C45*$B$30-'Debt Schedule'!H15)/Transaction!C26)^(1/Transaction!C45)-1) -> 0.37749008 | F30: =IF(Transaction!C26=0,0,((Transaction!C4*(1+F$25)^Transaction!C45*$B$30-'Debt Schedule'!H15)/Transaction!C26)^(1/Transaction!C45)-1) -> 0.41015395 | G30: =IF(Transaction!C26=0,0,((Transaction!C4*(1+G$25)^Transaction!C45*$B$30-'Debt Schedule'!H15)/Transaction!C26)^(1/Transaction!C45)-1) -> 0.45794871
