Workbook

Sheet Company Data
B1: COMPARABLE COMPANY ANALYSIS — DATA INPUT
B2: Enter company data below. Blue cells are user inputs. All amounts in $mm unless noted. Yellow cells = key inputs to populate first.
B3: IDENTIFICATION | E3: MARKET DATA & CAPITALIZATION | J3: FINANCIAL DATA ($mm) | Q3: KEY METRICS
B4: # | C4: Company Name | D4: Ticker | E4: Share Price ($) | F4: Shares Out (mm) | G4: Market Cap ($mm) | H4: Net Debt ($mm) | I4: Enterprise Value ($mm) | J4: LTM Revenue | K4: NTM Revenue | L4: LTM EBITDA | M4: NTM EBITDA | N4: LTM Net Income | O4: NTM Net Income | P4: LTM FCF | Q4: LTM Rev Growth | R4: NTM Rev Growth | S4: LTM EBITDA Margin | T4: NTM EBITDA Margin | U4: Net Margin | V4: ROE | W4: Dividend Yield
B5: 1 | C5: Company A | D5: CMPA | G5: =E5*F5 -> 0 | I5: =G5+H5 -> 0
B6: 2 | C6: Company B | D6: CMPB | G6: =E6*F6 -> 0 | I6: =G6+H6 -> 0
B7: 3 | C7: Company C | D7: CMPC | G7: =E7*F7 -> 0 | I7: =G7+H7 -> 0
B8: 4 | C8: Company D | D8: CMPD | G8: =E8*F8 -> 0 | I8: =G8+H8 -> 0
B9: 5 | C9: Company E | D9: CMPE | G9: =E9*F9 -> 0 | I9: =G9+H9 -> 0
B10: 6 | C10: Company F | D10: CMPF | G10: =E10*F10 -> 0 | I10: =G10+H10 -> 0
B11: 7 | C11: Company G | D11: CMPG | G11: =E11*F11 -> 0 | I11: =G11+H11 -> 0
B12: 8 | C12: Company H | D12: CMPH | G12: =E12*F12 -> 0 | I12: =G12+H12 -> 0
B13: 9 | C13: Company I | D13: CMPI | G13: =E13*F13 -> 0 | I13: =G13+H13 -> 0
B14: 10 | C14: Company J | D14: CMPJ | G14: =E14*F14 -> 0 | I14: =G14+H14 -> 0

Sheet Trading Multiples
B1: COMPARABLE COMPANY ANALYSIS — TRADING MULTIPLES
B3: COMPANY | E3: EV-BASED MULTIPLES | I3: EQUITY MULTIPLES | K3: YIELD & RETURNS
B4: # | C4: Company | D4: Ticker | E4: EV / LTM Rev | F4: EV / NTM Rev | G4: EV / LTM EBITDA | H4: EV / NTM EBITDA | I4: P / LTM E | J4: P / NTM E | K4: FCF Yield | L4: Dividend Yield | M4: EV / LTM FCF
B5: 1 | C5: ='Company Data'!C5 -> Company A | D5: ='Company Data'!D5 -> CMPA | E5: =IF('Company Data'!J5=0,0,'Company Data'!I5/'Company Data'!J5) -> 0 | F5: =IF('Company Data'!K5=0,0,'Company Data'!I5/'Company Data'!K5) -> 0 | G5: =IF('Company Data'!L5=0,0,'Company Data'!I5/'Company Data'!L5) -> 0 | H5: =IF('Company Data'!M5=0,0,'Company Data'!I5/'Company Data'!M5) -> 0 | I5: =IF('Company Data'!N5=0,0,'Company Data'!G5/'Company Data'!N5) -> 0 | J5: =IF('Company Data'!O5=0,0,'Company Data'!G5/'Company Data'!O5) -> 0 | K5: =IF('Company Data'!G5=0,0,'Company Data'!P5/'Company Data'!G5) -> 0 | L5: ='Company Data'!W5 -> 0 | M5: =IF('Company Data'!P5=0,0,'Company Data'!I5/'Company Data'!P5) -> 0
B6: 2 | C6: ='Company Data'!C6 -> Company B | D6: ='Company Data'!D6 -> CMPB | E6: =IF('Company Data'!J6=0,0,'Company Data'!I6/'Company Data'!J6) -> 0 | F6: =IF('Company Data'!K6=0,0,'Company Data'!I6/'Company Data'!K6) -> 0 | G6: =IF('Company Data'!L6=0,0,'Company Data'!I6/'Company Data'!L6) -> 0 | H6: =IF('Company Data'!M6=0,0,'Company Data'!I6/'Company Data'!M6) -> 0 | I6: =IF('Company Data'!N6=0,0,'Company Data'!G6/'Company Data'!N6) -> 0 | J6: =IF('Company Data'!O6=0,0,'Company Data'!G6/'Company Data'!O6) -> 0 | K6: =IF('Company Data'!G6=0,0,'Company Data'!P6/'Company Data'!G6) -> 0 | L6: ='Company Data'!W6 -> 0 | M6: =IF('Company Data'!P6=0,0,'Company Data'!I6/'Company Data'!P6) -> 0
B7: 3 | C7: ='Company Data'!C7 -> Company C | D7: ='Company Data'!D7 -> CMPC | E7: =IF('Company Data'!J7=0,0,'Company Data'!I7/'Company Data'!J7) -> 0 | F7: =IF('Company Data'!K7=0,0,'Company Data'!I7/'Company Data'!K7) -> 0 | G7: =IF('Company Data'!L7=0,0,'Company Data'!I7/'Company Data'!L7) -> 0 | H7: =IF('Company Data'!M7=0,0,'Company Data'!I7/'Company Data'!M7) -> 0 | I7: =IF('Company Data'!N7=0,0,'Company Data'!G7/'Company Data'!N7) -> 0 | J7: =IF('Company Data'!O7=0,0,'Company Data'!G7/'Company Data'!O7) -> 0 | K7: =IF('Company Data'!G7=0,0,'Company Data'!P7/'Company Data'!G7) -> 0 | L7: ='Company Data'!W7 -> 0 | M7: =IF('Company Data'!P7=0,0,'Company Data'!I7/'Company Data'!P7) -> 0
B8: 4 | C8: ='Company Data'!C8 -> Company D | D8: ='Company Data'!D8 -> CMPD | E8: =IF('Company Data'!J8=0,0,'Company Data'!I8/'Company Data'!J8) -> 0 | F8: =IF('Company Data'!K8=0,0,'Company Data'!I8/'Company Data'!K8) -> 0 | G8: =IF('Company Data'!L8=0,0,'Company Data'!I8/'Company Data'!L8) -> 0 | H8: =IF('Company Data'!M8=0,0,'Company Data'!I8/'Company Data'!M8) -> 0 | I8: =IF('Company Data'!N8=0,0,'Company Data'!G8/'Company Data'!N8) -> 0 | J8: =IF('Company Data'!O8=0,0,'Company Data'!G8/'Company Data'!O8) -> 0 | K8: =IF('Company Data'!G8=0,0,'Company Data'!P8/'Company Data'!G8) -> 0 | L8: ='Company Data'!W8 -> 0 | M8: =IF('Company Data'!P8=0,0,'Company Data'!I8/'Company Data'!P8) -> 0
B9: 5 | C9: ='Company Data'!C9 -> Company E | D9: ='Company Data'!D9 -> CMPE | E9: =IF('Company Data'!J9=0,0,'Company Data'!I9/'Company Data'!J9) -> 0 | F9: =IF('Company Data'!K9=0,0,'Company Data'!I9/'Company Data'!K9) -> 0 | G9: =IF('Company Data'!L9=0,0,'Company Data'!I9/'Company Data'!L9) -> 0 | H9: =IF('Company Data'!M9=0,0,'Company Data'!I9/'Company Data'!M9) -> 0 | I9: =IF('Company Data'!N9=0,0,'Company Data'!G9/'Company Data'!N9) -> 0 | J9: =IF('Company Data'!O9=0,0,'Company Data'!G9/'Company Data'!O9) -> 0 | K9: =IF('Company Data'!G9=0,0,'Company Data'!P9/'Company Data'!G9) -> 0 | L9: ='Company Data'!W9 -> 0 | M9: =IF('Company Data'!P9=0,0,'Company Data'!I9/'Company Data'!P9) -> 0
B10: 6 | C10: ='Company Data'!C10 -> Company F | D10: ='Company Data'!D10 -> CMPF | E10: =IF('Company Data'!J10=0,0,'Company Data'!I10/'Company Data'!J10) -> 0 | F10: =IF('Company Data'!K10=0,0,'Company Data'!I10/'Company Data'!K10) -> 0 | G10: =IF('Company Data'!L10=0,0,'Company Data'!I10/'Company Data'!L10) -> 0 | H10: =IF('Company Data'!M10=0,0,'Company Data'!I10/'Company Data'!M10) -> 0 | I10: =IF('Company Data'!N10=0,0,'Company Data'!G10/'Company Data'!N10) -> 0 | J10: =IF('Company Data'!O10=0,0,'Company Data'!G10/'Company Data'!O10) -> 0 | K10: =IF('Company Data'!G10=0,0,'Company Data'!P10/'Company Data'!G10) -> 0 | L10: ='Company Data'!W10 -> 0 | M10: =IF('Company Data'!P10=0,0,'Company Data'!I10/'Company Data'!P10) -> 0
B11: 7 | C11: ='Company Data'!C11 -> Company G | D11: ='Company Data'!D11 -> CMPG | E11: =IF('Company Data'!J11=0,0,'Company Data'!I11/'Company Data'!J11) -> 0 | F11: =IF('Company Data'!K11=0,0,'Company Data'!I11/'Company Data'!K11) -> 0 | G11: =IF('Company Data'!L11=0,0,'Company Data'!I11/'Company Data'!L11) -> 0 | H11: =IF('Company Data'!M11=0,0,'Company Data'!I11/'Company Data'!M11) -> 0 | I11: =IF('Company Data'!N11=0,0,'Company Data'!G11/'Company Data'!N11) -> 0 | J11: =IF('Company Data'!O11=0,0,'Company Data'!G11/'Company Data'!O11) -> 0 | K11: =IF('Company Data'!G11=0,0,'Company Data'!P11/'Company Data'!G11) -> 0 | L11: ='Company Data'!W11 -> 0 | M11: =IF('Company Data'!P11=0,0,'Company Data'!I11/'Company Data'!P11) -> 0
B12: 8 | C12: ='Company Data'!C12 -> Company H | D12: ='Company Data'!D12 -> CMPH | E12: =IF('Company Data'!J12=0,0,'Company Data'!I12/'Company Data'!J12) -> 0 | F12: =IF('Company Data'!K12=0,0,'Company Data'!I12/'Company Data'!K12) -> 0 | G12: =IF('Company Data'!L12=0,0,'Company Data'!I12/'Company Data'!L12) -> 0 | H12: =IF('Company Data'!M12=0,0,'Company Data'!I12/'Company Data'!M12) -> 0 | I12: =IF('Company Data'!N12=0,0,'Company Data'!G12/'Company Data'!N12) -> 0 | J12: =IF('Company Data'!O12=0,0,'Company Data'!G12/'Company Data'!O12) -> 0 | K12: =IF('Company Data'!G12=0,0,'Company Data'!P12/'Company Data'!G12) -> 0 | L12: ='Company Data'!W12 -> 0 | M12: =IF('Company Data'!P12=0,0,'Company Data'!I12/'Company Data'!P12) -> 0
B13: 9 | C13: ='Company Data'!C13 -> Company I | D13: ='Company Data'!D13 -> CMPI | E13: =IF('Company Data'!J13=0,0,'Company Data'!I13/'Company Data'!J13) -> 0 | F13: =IF('Company Data'!K13=0,0,'Company Data'!I13/'Company Data'!K13) -> 0 | G13: =IF('Company Data'!L13=0,0,'Company Data'!I13/'Company Data'!L13) -> 0 | H13: =IF('Company Data'!M13=0,0,'Company Data'!I13/'Company Data'!M13) -> 0 | I13: =IF('Company Data'!N13=0,0,'Company Data'!G13/'Company Data'!N13) -> 0 | J13: =IF('Company Data'!O13=0,0,'Company Data'!G13/'Company Data'!O13) -> 0 | K13: =IF('Company Data'!G13=0,0,'Company Data'!P13/'Company Data'!G13) -> 0 | L13: ='Company Data'!W13 -> 0 | M13: =IF('Company Data'!P13=0,0,'Company Data'!I13/'Company Data'!P13) -> 0
B14: 10 | C14: ='Company Data'!C14 -> Company J | D14: ='Company Data'!D14 -> CMPJ | E14: =IF('Company Data'!J14=0,0,'Company Data'!I14/'Company Data'!J14) -> 0 | F14: =IF('Company Data'!K14=0,0,'Company Data'!I14/'Company Data'!K14) -> 0 | G14: =IF('Company Data'!L14=0,0,'Company Data'!I14/'Company Data'!L14) -> 0 | H14: =IF('Company Data'!M14=0,0,'Company Data'!I14/'Company Data'!M14) -> 0 | I14: =IF('Company Data'!N14=0,0,'Company Data'!G14/'Company Data'!N14) -> 0 | J14: =IF('Company Data'!O14=0,0,'Company Data'!G14/'Company Data'!O14) -> 0 | K14: =IF('Company Data'!G14=0,0,'Company Data'!P14/'Company Data'!G14) -> 0 | L14: ='Company Data'!W14 -> 0 | M14: =IF('Company Data'!P14=0,0,'Company Data'!I14/'Company Data'!P14) -> 0
B16: SUMMARY STATISTICS
B17: Mean | E17: =IF(COUNT(E5:E14)=0,0,AVERAGE(E5:E14)) -> 0 | F17: =IF(COUNT(F5:F14)=0,0,AVERAGE(F5:F14)) -> 0 | G17: =IF(COUNT(G5:G14)=0,0,AVERAGE(G5:G14)) -> 0 | H17: =IF(COUNT(H5:H14)=0,0,AVERAGE(H5:H14)) -> 0 | I17: =IF(COUNT(I5:I14)=0,0,AVERAGE(I5:I14)) -> 0 | J17: =IF(COUNT(J5:J14)=0,0,AVERAGE(J5:J14)) -> 0 | K17: =IF(COUNT(K5:K14)=0,0,AVERAGE(K5:K14)) -> 0 | L17: =IF(COUNT(L5:L14)=0,0,AVERAGE(L5:L14)) -> 0 | M17: =IF(COUNT(M5:M14)=0,0,AVERAGE(M5:M14)) -> 0
B18: Median | E18: =IF(COUNT(E5:E14)=0,0,MEDIAN(E5:E14)) -> 0 | F18: =IF(COUNT(F5:F14)=0,0,MEDIAN(F5:F14)) -> 0 | G18: =IF(COUNT(G5:G14)=0,0,MEDIAN(G5:G14)) -> 0 | H18: =IF(COUNT(H5:H14)=0,0,MEDIAN(H5:H14)) -> 0 | I18: =IF(COUNT(I5:I14)=0,0,MEDIAN(I5:I14)) -> 0 | J18: =IF(COUNT(J5:J14)=0,0,MEDIAN(J5:J14)) -> 0 | K18: =IF(COUNT(K5:K14)=0,0,MEDIAN(K5:K14)) -> 0 | L18: =IF(COUNT(L5:L14)=0,0,MEDIAN(L5:L14)) -> 0 | M18: =IF(COUNT(M5:M14)=0,0,MEDIAN(M5:M14)) -> 0
B19: High | E19: =IF(COUNT(E5:E14)=0,0,MAX(E5:E14)) -> 0 | F19: =IF(COUNT(F5:F14)=0,0,MAX(F5:F14)) -> 0 | G19: =IF(COUNT(G5:G14)=0,0,MAX(G5:G14)) -> 0 | H19: =IF(COUNT(H5:H14)=0,0,MAX(H5:H14)) -> 0 | I19: =IF(COUNT(I5:I14)=0,0,MAX(I5:I14)) -> 0 | J19: =IF(COUNT(J5:J14)=0,0,MAX(J5:J14)) -> 0 | K19: =IF(COUNT(K5:K14)=0,0,MAX(K5:K14)) -> 0 | L19: =IF(COUNT(L5:L14)=0,0,MAX(L5:L14)) -> 0 | M19: =IF(COUNT(M5:M14)=0,0,MAX(M5:M14)) -> 0
B20: Low | E20: =IF(COUNT(E5:E14)=0,0,MIN(E5:E14)) -> 0 | F20: =IF(COUNT(F5:F14)=0,0,MIN(F5:F14)) -> 0 | G20: =IF(COUNT(G5:G14)=0,0,MIN(G5:G14)) -> 0 | H20: =IF(COUNT(H5:H14)=0,0,MIN(H5:H14)) -> 0 | I20: =IF(COUNT(I5:I14)=0,0,MIN(I5:I14)) -> 0 | J20: =IF(COUNT(J5:J14)=0,0,MIN(J5:J14)) -> 0 | K20: =IF(COUNT(K5:K14)=0,0,MIN(K5:K14)) -> 0 | L20: =IF(COUNT(L5:L14)=0,0,MIN(L5:L14)) -> 0 | M20: =IF(COUNT(M5:M14)=0,0,MIN(M5:M14)) -> 0
B21: 25th Percentile | E21: =IF(COUNT(E5:E14)=0,0,PERCENTILE(E5:E14,0.25)) -> 0 | F21: =IF(COUNT(F5:F14)=0,0,PERCENTILE(F5:F14,0.25)) -> 0 | G21: =IF(COUNT(G5:G14)=0,0,PERCENTILE(G5:G14,0.25)) -> 0 | H21: =IF(COUNT(H5:H14)=0,0,PERCENTILE(H5:H14,0.25)) -> 0 | I21: =IF(COUNT(I5:I14)=0,0,PERCENTILE(I5:I14,0.25)) -> 0 | J21: =IF(COUNT(J5:J14)=0,0,PERCENTILE(J5:J14,0.25)) -> 0 | K21: =IF(COUNT(K5:K14)=0,0,PERCENTILE(K5:K14,0.25)) -> 0 | L21: =IF(COUNT(L5:L14)=0,0,PERCENTILE(L5:L14,0.25)) -> 0 | M21: =IF(COUNT(M5:M14)=0,0,PERCENTILE(M5:M14,0.25)) -> 0
B22: 75th Percentile | E22: =IF(COUNT(E5:E14)=0,0,PERCENTILE(E5:E14,0.75)) -> 0 | F22: =IF(COUNT(F5:F14)=0,0,PERCENTILE(F5:F14,0.75)) -> 0 | G22: =IF(COUNT(G5:G14)=0,0,PERCENTILE(G5:G14,0.75)) -> 0 | H22: =IF(COUNT(H5:H14)=0,0,PERCENTILE(H5:H14,0.75)) -> 0 | I22: =IF(COUNT(I5:I14)=0,0,PERCENTILE(I5:I14,0.75)) -> 0 | J22: =IF(COUNT(J5:J14)=0,0,PERCENTILE(J5:J14,0.75)) -> 0 | K22: =IF(COUNT(K5:K14)=0,0,PERCENTILE(K5:K14,0.75)) -> 0 | L22: =IF(COUNT(L5:L14)=0,0,PERCENTILE(L5:L14,0.75)) -> 0 | M22: =IF(COUNT(M5:M14)=0,0,PERCENTILE(M5:M14,0.75)) -> 0

Sheet Implied Valuation
B1: IMPLIED VALUATION RANGE — TARGET COMPANY
B3: TARGET COMPANY DATA
B4: Target Company Name | C4: Enter Target Name
B5: Target Ticker | C5: TGT
B6: Current Share Price ($)
B7: Shares Outstanding (mm)
B8: Net Debt ($mm)
B9: LTM Revenue ($mm)
B10: NTM Revenue ($mm)
B11: LTM EBITDA ($mm)
B12: NTM EBITDA ($mm)
B13: LTM Net Income ($mm)
B14: NTM Net Income ($mm)
B15: LTM FCF ($mm)
B16: Market Cap ($mm) | C16: =C6*C7 -> 0
B17: Enterprise Value ($mm) | C17: =C16+C8 -> 0
B19: IMPLIED ENTERPRISE VALUE & EQUITY VALUE
B20: Metric | C20: Comp Median | D20: Implied EV ($mm) | E20: Implied Equity ($mm) | F20: Implied Price/Share
B21: EV / LTM Revenue | C21: ='Trading Multiples'!E18 -> 0 | D21: =C9*C21 -> 0 | E21: =D21-C8 -> 0 | F21: =IF(C7=0,0,E21/C7) -> 0
B22: EV / NTM Revenue | C22: ='Trading Multiples'!F18 -> 0 | D22: =C10*C22 -> 0 | E22: =D22-C8 -> 0 | F22: =IF(C7=0,0,E22/C7) -> 0
B23: EV / LTM EBITDA | C23: ='Trading Multiples'!G18 -> 0 | D23: =C11*C23 -> 0 | E23: =D23-C8 -> 0 | F23: =IF(C7=0,0,E23/C7) -> 0
B24: EV / NTM EBITDA | C24: ='Trading Multiples'!H18 -> 0 | D24: =C12*C24 -> 0 | E24: =D24-C8 -> 0 | F24: =IF(C7=0,0,E24/C7) -> 0
B25: P / LTM Earnings | C25: ='Trading Multiples'!I18 -> 0 | D25: =C13*C25+C8 -> 0 | E25: =C13*C25 -> 0 | F25: =IF(C7=0,0,E25/C7) -> 0
B26: P / NTM Earnings | C26: ='Trading Multiples'!J18 -> 0 | D26: =C14*C26+C8 -> 0 | E26: =C14*C26 -> 0 | F26: =IF(C7=0,0,E26/C7) -> 0
B28: VALUATION SUMMARY
B29: Implied Price Range
B30: Low | C30: =MIN(F20:F25) -> 0
B31: Median | C31: =MEDIAN(F20:F25) -> 0
B32: High | C32: =MAX(F20:F25) -> 0
B34: Current Share Price | C34: =C6 -> 0
B35: Upside / (Downside) to Median | C35: =IF(C34=0,0,C31/C34-1) -> 0

Sheet Benchmarking
B1: OPERATING BENCHMARKING
B3: COMPANY | E3: GROWTH METRICS | I3: PROFITABILITY | L3: RETURNS
B4: # | C4: Company | D4: Ticker | E4: LTM Rev Growth | F4: NTM Rev Growth | G4: LTM EBITDA Growth | H4: NTM EBITDA Growth | I4: LTM EBITDA Margin | J4: NTM EBITDA Margin | K4: Net Margin | L4: ROE | M4: FCF Yield
B5: 1 | C5: ='Company Data'!C5 -> Company A | D5: ='Company Data'!D5 -> CMPA | E5: ='Company Data'!Q5 -> 0 | F5: ='Company Data'!R5 -> 0 | I5: ='Company Data'!S5 -> 0 | J5: ='Company Data'!T5 -> 0 | K5: ='Company Data'!U5 -> 0 | L5: ='Company Data'!V5 -> 0 | M5: ='Trading Multiples'!K5 -> 0
B6: 2 | C6: ='Company Data'!C6 -> Company B | D6: ='Company Data'!D6 -> CMPB | E6: ='Company Data'!Q6 -> 0 | F6: ='Company Data'!R6 -> 0 | I6: ='Company Data'!S6 -> 0 | J6: ='Company Data'!T6 -> 0 | K6: ='Company Data'!U6 -> 0 | L6: ='Company Data'!V6 -> 0 | M6: ='Trading Multiples'!K6 -> 0
B7: 3 | C7: ='Company Data'!C7 -> Company C | D7: ='Company Data'!D7 -> CMPC | E7: ='Company Data'!Q7 -> 0 | F7: ='Company Data'!R7 -> 0 | I7: ='Company Data'!S7 -> 0 | J7: ='Company Data'!T7 -> 0 | K7: ='Company Data'!U7 -> 0 | L7: ='Company Data'!V7 -> 0 | M7: ='Trading Multiples'!K7 -> 0
B8: 4 | C8: ='Company Data'!C8 -> Company D | D8: ='Company Data'!D8 -> CMPD | E8: ='Company Data'!Q8 -> 0 | F8: ='Company Data'!R8 -> 0 | I8: ='Company Data'!S8 -> 0 | J8: ='Company Data'!T8 -> 0 | K8: ='Company Data'!U8 -> 0 | L8: ='Company Data'!V8 -> 0 | M8: ='Trading Multiples'!K8 -> 0
B9: 5 | C9: ='Company Data'!C9 -> Company E | D9: ='Company Data'!D9 -> CMPE | E9: ='Company Data'!Q9 -> 0 | F9: ='Company Data'!R9 -> 0 | I9: ='Company Data'!S9 -> 0 | J9: ='Company Data'!T9 -> 0 | K9: ='Company Data'!U9 -> 0 | L9: ='Company Data'!V9 -> 0 | M9: ='Trading Multiples'!K9 -> 0
B10: 6 | C10: ='Company Data'!C10 -> Company F | D10: ='Company Data'!D10 -> CMPF | E10: ='Company Data'!Q10 -> 0 | F10: ='Company Data'!R10 -> 0 | I10: ='Company Data'!S10 -> 0 | J10: ='Company Data'!T10 -> 0 | K10: ='Company Data'!U10 -> 0 | L10: ='Company Data'!V10 -> 0 | M10: ='Trading Multiples'!K10 -> 0
B11: 7 | C11: ='Company Data'!C11 -> Company G | D11: ='Company Data'!D11 -> CMPG | E11: ='Company Data'!Q11 -> 0 | F11: ='Company Data'!R11 -> 0 | I11: ='Company Data'!S11 -> 0 | J11: ='Company Data'!T11 -> 0 | K11: ='Company Data'!U11 -> 0 | L11: ='Company Data'!V11 -> 0 | M11: ='Trading Multiples'!K11 -> 0
B12: 8 | C12: ='Company Data'!C12 -> Company H | D12: ='Company Data'!D12 -> CMPH | E12: ='Company Data'!Q12 -> 0 | F12: ='Company Data'!R12 -> 0 | I12: ='Company Data'!S12 -> 0 | J12: ='Company Data'!T12 -> 0 | K12: ='Company Data'!U12 -> 0 | L12: ='Company Data'!V12 -> 0 | M12: ='Trading Multiples'!K12 -> 0
B13: 9 | C13: ='Company Data'!C13 -> Company I | D13: ='Company Data'!D13 -> CMPI | E13: ='Company Data'!Q13 -> 0 | F13: ='Company Data'!R13 -> 0 | I13: ='Company Data'!S13 -> 0 | J13: ='Company Data'!T13 -> 0 | K13: ='Company Data'!U13 -> 0 | L13: ='Company Data'!V13 -> 0 | M13: ='Trading Multiples'!K13 -> 0
B14: 10 | C14: ='Company Data'!C14 -> Company J | D14: ='Company Data'!D14 -> CMPJ | E14: ='Company Data'!Q14 -> 0 | F14: ='Company Data'!R14 -> 0 | I14: ='Company Data'!S14 -> 0 | J14: ='Company Data'!T14 -> 0 | K14: ='Company Data'!U14 -> 0 | L14: ='Company Data'!V14 -> 0 | M14: ='Trading Multiples'!K14 -> 0
B16: SUMMARY STATISTICS
B17: Mean | E17: =IF(COUNT(E5:E14)=0,0,AVERAGE(E5:E14)) -> 0 | F17: =IF(COUNT(F5:F14)=0,0,AVERAGE(F5:F14)) -> 0 | G17: =IF(COUNT(G5:G14)=0,0,AVERAGE(G5:G14)) -> 0 | H17: =IF(COUNT(H5:H14)=0,0,AVERAGE(H5:H14)) -> 0 | I17: =IF(COUNT(I5:I14)=0,0,AVERAGE(I5:I14)) -> 0 | J17: =IF(COUNT(J5:J14)=0,0,AVERAGE(J5:J14)) -> 0 | K17: =IF(COUNT(K5:K14)=0,0,AVERAGE(K5:K14)) -> 0 | L17: =IF(COUNT(L5:L14)=0,0,AVERAGE(L5:L14)) -> 0 | M17: =IF(COUNT(M5:M14)=0,0,AVERAGE(M5:M14)) -> 0
B18: Median | E18: =IF(COUNT(E5:E14)=0,0,MEDIAN(E5:E14)) -> 0 | F18: =IF(COUNT(F5:F14)=0,0,MEDIAN(F5:F14)) -> 0 | G18: =IF(COUNT(G5:G14)=0,0,MEDIAN(G5:G14)) -> 0 | H18: =IF(COUNT(H5:H14)=0,0,MEDIAN(H5:H14)) -> 0 | I18: =IF(COUNT(I5:I14)=0,0,MEDIAN(I5:I14)) -> 0 | J18: =IF(COUNT(J5:J14)=0,0,MEDIAN(J5:J14)) -> 0 | K18: =IF(COUNT(K5:K14)=0,0,MEDIAN(K5:K14)) -> 0 | L18: =IF(COUNT(L5:L14)=0,0,MEDIAN(L5:L14)) -> 0 | M18: =IF(COUNT(M5:M14)=0,0,MEDIAN(M5:M14)) -> 0
B19: High | E19: =IF(COUNT(E5:E14)=0,0,MAX(E5:E14)) -> 0 | F19: =IF(COUNT(F5:F14)=0,0,MAX(F5:F14)) -> 0 | G19: =IF(COUNT(G5:G14)=0,0,MAX(G5:G14)) -> 0 | H19: =IF(COUNT(H5:H14)=0,0,MAX(H5:H14)) -> 0 | I19: =IF(COUNT(I5:I14)=0,0,MAX(I5:I14)) -> 0 | J19: =IF(COUNT(J5:J14)=0,0,MAX(J5:J14)) -> 0 | K19: =IF(COUNT(K5:K14)=0,0,MAX(K5:K14)) -> 0 | L19: =IF(COUNT(L5:L14)=0,0,MAX(L5:L14)) -> 0 | M19: =IF(COUNT(M5:M14)=0,0,MAX(M5:M14)) -> 0
B20: Low | E20: =IF(COUNT(E5:E14)=0,0,MIN(E5:E14)) -> 0 | F20: =IF(COUNT(F5:F14)=0,0,MIN(F5:F14)) -> 0 | G20: =IF(COUNT(G5:G14)=0,0,MIN(G5:G14)) -> 0 | H20: =IF(COUNT(H5:H14)=0,0,MIN(H5:H14)) -> 0 | I20: =IF(COUNT(I5:I14)=0,0,MIN(I5:I14)) -> 0 | J20: =IF(COUNT(J5:J14)=0,0,MIN(J5:J14)) -> 0 | K20: =IF(COUNT(K5:K14)=0,0,MIN(K5:K14)) -> 0 | L20: =IF(COUNT(L5:L14)=0,0,MIN(L5:L14)) -> 0 | M20: =IF(COUNT(M5:M14)=0,0,MIN(M5:M14)) -> 0
B21: 25th Percentile | E21: =IF(COUNT(E5:E14)=0,0,PERCENTILE(E5:E14,0.25)) -> 0 | F21: =IF(COUNT(F5:F14)=0,0,PERCENTILE(F5:F14,0.25)) -> 0 | G21: =IF(COUNT(G5:G14)=0,0,PERCENTILE(G5:G14,0.25)) -> 0 | H21: =IF(COUNT(H5:H14)=0,0,PERCENTILE(H5:H14,0.25)) -> 0 | I21: =IF(COUNT(I5:I14)=0,0,PERCENTILE(I5:I14,0.25)) -> 0 | J21: =IF(COUNT(J5:J14)=0,0,PERCENTILE(J5:J14,0.25)) -> 0 | K21: =IF(COUNT(K5:K14)=0,0,PERCENTILE(K5:K14,0.25)) -> 0 | L21: =IF(COUNT(L5:L14)=0,0,PERCENTILE(L5:L14,0.25)) -> 0 | M21: =IF(COUNT(M5:M14)=0,0,PERCENTILE(M5:M14,0.25)) -> 0
B22: 75th Percentile | E22: =IF(COUNT(E5:E14)=0,0,PERCENTILE(E5:E14,0.75)) -> 0 | F22: =IF(COUNT(F5:F14)=0,0,PERCENTILE(F5:F14,0.75)) -> 0 | G22: =IF(COUNT(G5:G14)=0,0,PERCENTILE(G5:G14,0.75)) -> 0 | H22: =IF(COUNT(H5:H14)=0,0,PERCENTILE(H5:H14,0.75)) -> 0 | I22: =IF(COUNT(I5:I14)=0,0,PERCENTILE(I5:I14,0.75)) -> 0 | J22: =IF(COUNT(J5:J14)=0,0,PERCENTILE(J5:J14,0.75)) -> 0 | K22: =IF(COUNT(K5:K14)=0,0,PERCENTILE(K5:K14,0.75)) -> 0 | L22: =IF(COUNT(L5:L14)=0,0,PERCENTILE(L5:L14,0.75)) -> 0 | M22: =IF(COUNT(M5:M14)=0,0,PERCENTILE(M5:M14,0.75)) -> 0
